log_lammps_reader-0.4.0.dist-info/METADATA
log_lammps_reader-0.4.0.dist-info/WHEEL
log_lammps_reader-0.4.0.dist-info/licenses/LICENSE
log_lammps_reader/__init__.py
log_lammps_reader/log_lammps_reader.pypy311-pp73-ppc_64-linux-gnu.so
log_lammps_reader-0.4.0.dist-info/RECORD
