Metadata-Version: 2.4
Name: log_lammps_reader
Version: 0.4.0
Classifier: Programming Language :: Rust
Classifier: Programming Language :: Python :: Implementation :: CPython
Classifier: Programming Language :: Python :: Implementation :: PyPy
License-File: LICENSE
Summary: High-performance Rust library and Python extension for reading LAMMPS log files
Keywords: lammps,lammps logfile,lammps log,log reader,polars rust
Author-email: Geordy Jomon <gj82@njit.edu>
License: MIT License
Requires-Python: >=3.8
Project-URL: Repository, https://github.com/GeordyJ/log_lammps_reader
Project-URL: Issues, https://github.com/GeordyJ/log_lammps_reader/issues
